jupyter_jsonnet/__init__.py
jupyter_jsonnet/kernel.py
jupyter_jsonnet/post_install.py
jupyter_jsonnet/tests/__init__.py
jupyter_jsonnet/tests/test_kernel.py
jupyter_jsonnet-0.4.dist-info/LICENSE
jupyter_jsonnet-0.4.dist-info/METADATA
jupyter_jsonnet-0.4.dist-info/WHEEL
jupyter_jsonnet-0.4.dist-info/top_level.txt
jupyter_jsonnet-0.4.dist-info/RECORD
