Metadata-Version: 2.1
Name: jupyter-jsonnet
Version: 0.4
Summary: A simple Jsonnet kernel for Jupyter
Author-email: Aaron Bentley <aaron@aaronbentley.com>
License: MIT
Project-URL: repository, https://github.com/abentley/jupyter-jsonnet
Classifier: Framework :: Jupyter
Classifier: Development Status :: 3 - Alpha
Classifier: Programming Language :: Python :: 3
Classifier: License :: OSI Approved :: MIT License
License-File: LICENSE
Requires-Dist: ipykernel
Requires-Dist: jsonnet
Requires-Dist: jupyter-client
Requires-Dist: notebook
